thqm/__cli__.py
thqm/__init__.py
thqm/server.py
thqm/settings.py
thqm/styles/default/static/favicon.png
thqm/styles/default/static/index.css
thqm/styles/default/static/power-off-icon.svg
thqm/styles/default/static/qrcode-icon.svg
thqm/styles/default/template/index.html
thqm/styles/fa-grid/static/favicon.png
thqm/styles/fa-grid/static/fontawesome/all.js
thqm/styles/fa-grid/static/index.css
thqm/styles/fa-grid/static/power-off-icon.svg
thqm/styles/fa-grid/static/qrcode-icon.svg
thqm/styles/fa-grid/template/index.html
thqm/utils.py
thqm-1.4.0.dist-info/entry_points.txt
thqm-1.4.0.dist-info/LICENSE
thqm-1.4.0.dist-info/WHEEL
thqm-1.4.0.dist-info/METADATA
thqm-1.4.0.dist-info/RECORD
