Metadata-Version: 2.1
Name: thqm
Version: 1.4.0
Summary: remote command execution made easy.
Home-page: https://github.com/loiccoyle/thqm
License: MIT
Keywords: remote,command,HTTP-server,thqm
Author: Loic Coyle
Author-email: loic.coyle@hotmail.fr
Requires-Python: >=3.6.1
Classifier: License :: OSI Approved :: MIT License
Classifier: Operating System :: MacOS
Classifier: Operating System :: Microsoft :: Windows
Classifier: Operating System :: Unix
Classifier: Programming Language :: Python
Classifier: Programming Language :: Python :: 3
Classifier: Programming Language :: Python :: 3.10
Classifier: Programming Language :: Python :: 3.7
Classifier: Programming Language :: Python :: 3.8
Classifier: Programming Language :: Python :: 3.9
Classifier: Topic :: Home Automation
Classifier: Topic :: Internet :: WWW/HTTP :: HTTP Servers
Classifier: Topic :: Utilities
Provides-Extra: qrcode
Requires-Dist: jinja2 (>=3.0.0,<4.0.0)
Requires-Dist: netifaces (>=0.11.0,<0.12.0)
Requires-Dist: pypng (>=0.0.20,<0.0.21); extra == "qrcode"
Requires-Dist: pyqrcode (>=1.2.1,<2.0.0); extra == "qrcode"
Project-URL: Repository, https://github.com/loiccoyle/thqm
